{"name":"outposts","actions":{"CancelCapacityTask":{"name":"CancelCapacityTask","service":"outposts","conditionKeys":[],"resources":[{"name":"outpost"}],"description":"Grants permission to cancel a capacity task","accessLevel":"Write","resourceTypes":[{"name":"outpost","required":true}],"operationUrl":"https://docs.aws.amazon.com/outposts/latest/APIReference/API_CancelCapacityTask.html","iamUrl":"https://docs.aws.amazon.com/service-authorization/latest/reference/list_awsoutposts.html#awsoutposts-CancelCapacityTask"},"CancelOrder":{"name":"CancelOrder","service":"outposts","conditionKeys":[],"resources":[],"description":"Grants permission to cancel an order","accessLevel":"Write","resourceTypes":[],"operationUrl":"https://docs.aws.amazon.com/outposts/latest/APIReference/API_CancelOrder.html","iamUrl":"https://docs.aws.amazon.com/service-authorization/latest/reference/list_awsoutposts.html#awsoutposts-CancelOrder"},"CreateOrder":{"name":"CreateOrder","service":"outposts","conditionKeys":[],"resources":[{"name":"outpost"}],"description":"Grants permission to create an order","accessLevel":"Write","resourceTypes":[{"name":"outpost","required":true}],"operationUrl":"https://docs.aws.amazon.com/outposts/latest/APIReference/API_CreateOrder.html","iamUrl":"https://docs.aws.amazon.com/service-authorization/latest/reference/list_awsoutposts.html#awsoutposts-CreateOrder"},"CreateOutpost":{"name":"CreateOutpost","service":"outposts","conditionKeys":["aws:RequestTag/${TagKey}","aws:ResourceTag/${TagKey}","aws:TagKeys"],"resources":[{"name":"site"}],"description":"Grants permission to create an Outpost","accessLevel":"Write","resourceTypes":[{"name":"site","required":true}],"operationUrl":"https://docs.aws.amazon.com/outposts/latest/APIReference/API_CreateOutpost.html","iamUrl":"https://docs.aws.amazon.com/service-authorization/latest/reference/list_awsoutposts.html#awsoutposts-CreateOutpost"},"CreatePrivateConnectivityConfig":{"name":"CreatePrivateConnectivityConfig","service":"outposts","conditionKeys":[],"resources":[{"name":"outpost"}],"description":"Grants permission to create a private connectivity configuration","accessLevel":"Write","resourceTypes":[{"name":"outpost","required":true}],"operationUrl":"https://docs.aws.amazon.com/outposts/latest/userguide/how-outposts-works.html#private-connectivity","iamUrl":"https://docs.aws.amazon.com/service-authorization/latest/reference/list_awsoutposts.html#awsoutposts-CreatePrivateConnectivityConfig"},"CreateSite":{"name":"CreateSite","service":"outposts","conditionKeys":["aws:RequestTag/${TagKey}","aws:ResourceTag/${TagKey}","aws:TagKeys"],"resources":[],"description":"Grants permission to create a site","accessLevel":"Write","resourceTypes":[],"operationUrl":"https://docs.aws.amazon.com/outposts/latest/APIReference/API_CreateSite.html","iamUrl":"https://docs.aws.amazon.com/service-authorization/latest/reference/list_awsoutposts.html#awsoutposts-CreateSite"},"DeleteOutpost":{"name":"DeleteOutpost","service":"outposts","conditionKeys":[],"resources":[{"name":"outpost"}],"description":"Grants permission to delete an Outpost","accessLevel":"Write","resourceTypes":[{"name":"outpost","required":true}],"operationUrl":"https://docs.aws.amazon.com/outposts/latest/APIReference/API_DeleteOutpost.html","iamUrl":"https://docs.aws.amazon.com/service-authorization/latest/reference/list_awsoutposts.html#awsoutposts-DeleteOutpost"},"DeleteSite":{"name":"DeleteSite","service":"outposts","conditionKeys":[],"resources":[{"name":"site"}],"description":"Grants permission to delete a site","accessLevel":"Write","resourceTypes":[{"name":"site","required":true}],"operationUrl":"https://docs.aws.amazon.com/outposts/latest/APIReference/API_DeleteSite.html","iamUrl":"https://docs.aws.amazon.com/service-authorization/latest/reference/list_awsoutposts.html#awsoutposts-DeleteSite"},"GetCapacityTask":{"name":"GetCapacityTask","service":"outposts","conditionKeys":[],"resources":[{"name":"outpost"}],"description":"Grants permission to get information about the specified capacity task","accessLevel":"Read","resourceTypes":[{"name":"outpost","required":true}],"operationUrl":"https://docs.aws.amazon.com/outposts/latest/APIReference/API_GetCapacityTask.html","iamUrl":"https://docs.aws.amazon.com/service-authorization/latest/reference/list_awsoutposts.html#awsoutposts-GetCapacityTask"},"GetCatalogItem":{"name":"GetCatalogItem","service":"outposts","conditionKeys":[],"resources":[],"description":"Grants permission to get a catalog item","accessLevel":"Read","resourceTypes":[],"operationUrl":"https://docs.aws.amazon.com/outposts/latest/APIReference/API_GetCatalogItem.html","iamUrl":"https://docs.aws.amazon.com/service-authorization/latest/reference/list_awsoutposts.html#awsoutposts-GetCatalogItem"},"GetConnection":{"name":"GetConnection","service":"outposts","conditionKeys":[],"resources":[],"description":"Grants permission to get information about the connection for your Outpost server","accessLevel":"Read","resourceTypes":[],"operationUrl":"https://docs.aws.amazon.com/outposts/latest/APIReference/API_GetConnection.html","iamUrl":"https://docs.aws.amazon.com/service-authorization/latest/reference/list_awsoutposts.html#awsoutposts-GetConnection"},"GetOrder":{"name":"GetOrder","service":"outposts","conditionKeys":[],"resources":[],"description":"Grants permission to get information about an order","accessLevel":"Read","resourceTypes":[],"operationUrl":"https://docs.aws.amazon.com/outposts/latest/APIReference/API_GetOrder.html","iamUrl":"https://docs.aws.amazon.com/service-authorization/latest/reference/list_awsoutposts.html#awsoutposts-GetOrder"},"GetOutpost":{"name":"GetOutpost","service":"outposts","conditionKeys":[],"resources":[{"name":"outpost"}],"description":"Grants permission to get information about the specified Outpost","accessLevel":"Read","resourceTypes":[{"name":"outpost","required":true}],"operationUrl":"https://docs.aws.amazon.com/outposts/latest/APIReference/API_GetOutpost.html","iamUrl":"https://docs.aws.amazon.com/service-authorization/latest/reference/list_awsoutposts.html#awsoutposts-GetOutpost"},"GetOutpostBillingInformation":{"name":"GetOutpostBillingInformation","service":"outposts","conditionKeys":[],"resources":[{"name":"outpost"}],"description":"Grants permission to get Outpost billing information for the specified Outpost","accessLevel":"Read","resourceTypes":[{"name":"outpost","required":true}],"operationUrl":"https://docs.aws.amazon.com/outposts/latest/APIReference/API_GetOutpostBillingInformation.html","iamUrl":"https://docs.aws.amazon.com/service-authorization/latest/reference/list_awsoutposts.html#awsoutposts-GetOutpostBillingInformation"},"GetOutpostInstanceTypes":{"name":"GetOutpostInstanceTypes","service":"outposts","conditionKeys":[],"resources":[{"name":"outpost"}],"description":"Grants permission to get the instance types for the specified Outpost","accessLevel":"Read","resourceTypes":[{"name":"outpost","required":true}],"operationUrl":"https://docs.aws.amazon.com/outposts/latest/APIReference/API_GetOutpostInstanceTypes.html","iamUrl":"https://docs.aws.amazon.com/service-authorization/latest/reference/list_awsoutposts.html#awsoutposts-GetOutpostInstanceTypes"},"GetOutpostSupportedInstanceTypes":{"name":"GetOutpostSupportedInstanceTypes","service":"outposts","conditionKeys":[],"resources":[{"name":"outpost"}],"description":"Grants permission to get the supported instance types for the specified Outpost","accessLevel":"Read","resourceTypes":[{"name":"outpost","required":true}],"operationUrl":"https://docs.aws.amazon.com/outposts/latest/APIReference/API_GetOutpostSupportedInstanceTypes.html","iamUrl":"https://docs.aws.amazon.com/service-authorization/latest/reference/list_awsoutposts.html#awsoutposts-GetOutpostSupportedInstanceTypes"},"GetPrivateConnectivityConfig":{"name":"GetPrivateConnectivityConfig","service":"outposts","conditionKeys":[],"resources":[{"name":"outpost"}],"description":"Grants permission to get a private connectivity configuration","accessLevel":"Read","resourceTypes":[{"name":"outpost","required":true}],"operationUrl":"https://docs.aws.amazon.com/outposts/latest/userguide/how-outposts-works.html#private-connectivity","iamUrl":"https://docs.aws.amazon.com/service-authorization/latest/reference/list_awsoutposts.html#awsoutposts-GetPrivateConnectivityConfig"},"GetSite":{"name":"GetSite","service":"outposts","conditionKeys":[],"resources":[{"name":"site"}],"description":"Grants permission to get a site","accessLevel":"Read","resourceTypes":[{"name":"site","required":true}],"operationUrl":"https://docs.aws.amazon.com/outposts/latest/APIReference/API_GetSite.html","iamUrl":"https://docs.aws.amazon.com/service-authorization/latest/reference/list_awsoutposts.html#awsoutposts-GetSite"},"GetSiteAddress":{"name":"GetSiteAddress","service":"outposts","conditionKeys":[],"resources":[{"name":"site"}],"description":"Grants permission to get a site address","accessLevel":"Read","resourceTypes":[{"name":"site","required":true}],"operationUrl":"https://docs.aws.amazon.com/outposts/latest/APIReference/API_GetSiteAddress.html","iamUrl":"https://docs.aws.amazon.com/service-authorization/latest/reference/list_awsoutposts.html#awsoutposts-GetSiteAddress"},"ListAssetInstances":{"name":"ListAssetInstances","service":"outposts","conditionKeys":[],"resources":[{"name":"outpost"}],"description":"Grants permission to list all running instances for the specified Outpost","accessLevel":"List","resourceTypes":[{"name":"outpost","required":true}],"operationUrl":"https://docs.aws.amazon.com/outposts/latest/APIReference/API_ListAssetInstances.html","iamUrl":"https://docs.aws.amazon.com/service-authorization/latest/reference/list_awsoutposts.html#awsoutposts-ListAssetInstances"},"ListAssets":{"name":"ListAssets","service":"outposts","conditionKeys":[],"resources":[{"name":"outpost"}],"description":"Grants permission to list the assets for your Outpost","accessLevel":"List","resourceTypes":[{"name":"outpost","required":true}],"operationUrl":"https://docs.aws.amazon.com/outposts/latest/APIReference/API_ListAssets.html","iamUrl":"https://docs.aws.amazon.com/service-authorization/latest/reference/list_awsoutposts.html#awsoutposts-ListAssets"},"ListBlockingInstancesForCapacityTask":{"name":"ListBlockingInstancesForCapacityTask","service":"outposts","conditionKeys":[],"resources":[{"name":"outpost"}],"description":"Grants permission to list all running instances that are blocking the capacity task from running for the specified Outpost","accessLevel":"List","resourceTypes":[{"name":"outpost","required":true}],"operationUrl":"https://docs.aws.amazon.com/outposts/latest/APIReference/API_ListBlockingInstancesForCapacityTask.html","iamUrl":"https://docs.aws.amazon.com/service-authorization/latest/reference/list_awsoutposts.html#awsoutposts-ListBlockingInstancesForCapacityTask"},"ListCapacityTasks":{"name":"ListCapacityTasks","service":"outposts","conditionKeys":[],"resources":[],"description":"Grants permission to list the capacity tasks for your AWS account","accessLevel":"List","resourceTypes":[],"operationUrl":"https://docs.aws.amazon.com/outposts/latest/APIReference/API_ListCapacityTasks.html","iamUrl":"https://docs.aws.amazon.com/service-authorization/latest/reference/list_awsoutposts.html#awsoutposts-ListCapacityTasks"},"ListCatalogItems":{"name":"ListCatalogItems","service":"outposts","conditionKeys":[],"resources":[],"description":"Grants permission to list all catalog items","accessLevel":"List","resourceTypes":[],"operationUrl":"https://docs.aws.amazon.com/outposts/latest/APIReference/API_ListCatalogItems.html","iamUrl":"https://docs.aws.amazon.com/service-authorization/latest/reference/list_awsoutposts.html#awsoutposts-ListCatalogItems"},"ListOrders":{"name":"ListOrders","service":"outposts","conditionKeys":[],"resources":[],"description":"Grants permission to list the orders for your AWS account","accessLevel":"List","resourceTypes":[],"operationUrl":"https://docs.aws.amazon.com/outposts/latest/APIReference/API_ListOrders.html","iamUrl":"https://docs.aws.amazon.com/service-authorization/latest/reference/list_awsoutposts.html#awsoutposts-ListOrders"},"ListOutposts":{"name":"ListOutposts","service":"outposts","conditionKeys":[],"resources":[],"description":"Grants permission to list the Outposts for your AWS account","accessLevel":"List","resourceTypes":[],"operationUrl":"https://docs.aws.amazon.com/outposts/latest/APIReference/API_ListOutposts.html","iamUrl":"https://docs.aws.amazon.com/service-authorization/latest/reference/list_awsoutposts.html#awsoutposts-ListOutposts"},"ListSites":{"name":"ListSites","service":"outposts","conditionKeys":[],"resources":[],"description":"Grants permission to list the sites for your AWS account","accessLevel":"List","resourceTypes":[],"operationUrl":"https://docs.aws.amazon.com/outposts/latest/APIReference/API_ListSites.html","iamUrl":"https://docs.aws.amazon.com/service-authorization/latest/reference/list_awsoutposts.html#awsoutposts-ListSites"},"ListTagsForResource":{"name":"ListTagsForResource","service":"outposts","conditionKeys":[],"resources":[],"description":"Grants permission to list tags for a resource","accessLevel":"Read","resourceTypes":[],"operationUrl":"https://docs.aws.amazon.com/outposts/latest/APIReference/API_ListTagsForResource.html","iamUrl":"https://docs.aws.amazon.com/service-authorization/latest/reference/list_awsoutposts.html#awsoutposts-ListTagsForResource"},"StartCapacityTask":{"name":"StartCapacityTask","service":"outposts","conditionKeys":[],"resources":[{"name":"outpost"}],"description":"Grants permission to create a capacity task","accessLevel":"Write","resourceTypes":[{"name":"outpost","required":true}],"operationUrl":"https://docs.aws.amazon.com/outposts/latest/APIReference/API_StartCapacityTask.html","iamUrl":"https://docs.aws.amazon.com/service-authorization/latest/reference/list_awsoutposts.html#awsoutposts-StartCapacityTask"},"StartConnection":{"name":"StartConnection","service":"outposts","conditionKeys":[],"resources":[],"description":"Grants permission to start a connection for your Outpost server","accessLevel":"Write","resourceTypes":[],"operationUrl":"https://docs.aws.amazon.com/outposts/latest/APIReference/API_StartConnection.html","iamUrl":"https://docs.aws.amazon.com/service-authorization/latest/reference/list_awsoutposts.html#awsoutposts-StartConnection"},"TagResource":{"name":"TagResource","service":"outposts","conditionKeys":["aws:RequestTag/${TagKey}","aws:TagKeys"],"resources":[{"name":"outpost"},{"name":"site"}],"description":"Grants permission to tag a resource","accessLevel":"Tagging","resourceTypes":[{"name":"outpost","required":false},{"name":"site","required":false}],"operationUrl":"https://docs.aws.amazon.com/outposts/latest/APIReference/API_TagResource.html","iamUrl":"https://docs.aws.amazon.com/service-authorization/latest/reference/list_awsoutposts.html#awsoutposts-TagResource"},"UntagResource":{"name":"UntagResource","service":"outposts","conditionKeys":["aws:TagKeys"],"resources":[{"name":"outpost"},{"name":"site"}],"description":"Grants permission to untag a resource","accessLevel":"Tagging","resourceTypes":[{"name":"outpost","required":false},{"name":"site","required":false}],"operationUrl":"https://docs.aws.amazon.com/outposts/latest/APIReference/API_UntagResource.html","iamUrl":"https://docs.aws.amazon.com/service-authorization/latest/reference/list_awsoutposts.html#awsoutposts-UntagResource"},"UpdateOutpost":{"name":"UpdateOutpost","service":"outposts","conditionKeys":[],"resources":[{"name":"outpost"}],"description":"Grants permission to update an Outpost","accessLevel":"Write","resourceTypes":[{"name":"outpost","required":true}],"operationUrl":"https://docs.aws.amazon.com/outposts/latest/APIReference/API_UpdateOutpost.html","iamUrl":"https://docs.aws.amazon.com/service-authorization/latest/reference/list_awsoutposts.html#awsoutposts-UpdateOutpost"},"UpdateSite":{"name":"UpdateSite","service":"outposts","conditionKeys":[],"resources":[{"name":"site"}],"description":"Grants permission to update a site","accessLevel":"Write","resourceTypes":[{"name":"site","required":true}],"operationUrl":"https://docs.aws.amazon.com/outposts/latest/APIReference/API_UpdateSite.html","iamUrl":"https://docs.aws.amazon.com/service-authorization/latest/reference/list_awsoutposts.html#awsoutposts-UpdateSite"},"UpdateSiteAddress":{"name":"UpdateSiteAddress","service":"outposts","conditionKeys":[],"resources":[{"name":"site"}],"description":"Grants permission to update the site address","accessLevel":"Write","resourceTypes":[{"name":"site","required":true}],"operationUrl":"https://docs.aws.amazon.com/outposts/latest/APIReference/API_UpdateSiteAddress.html","iamUrl":"https://docs.aws.amazon.com/service-authorization/latest/reference/list_awsoutposts.html#awsoutposts-UpdateSiteAddress"},"UpdateSiteRackPhysicalProperties":{"name":"UpdateSiteRackPhysicalProperties","service":"outposts","conditionKeys":[],"resources":[{"name":"site"}],"description":"Grants permission to update the physical properties of a rack at a site","accessLevel":"Write","resourceTypes":[{"name":"site","required":true}],"operationUrl":"https://docs.aws.amazon.com/outposts/latest/APIReference/API_UpdateSiteRackPhysicalProperties.html","iamUrl":"https://docs.aws.amazon.com/service-authorization/latest/reference/list_awsoutposts.html#awsoutposts-UpdateSiteRackPhysicalProperties"}},"resources":[{"service":"outposts","name":"outpost","arnFormats":["arn:${Partition}:outposts:${Region}:${Account}:outpost/${OutpostId}"],"conditionKeys":["aws:ResourceTag/${TagKey}"]},{"service":"outposts","name":"site","arnFormats":["arn:${Partition}:outposts:${Region}:${Account}:site/${SiteId}"],"conditionKeys":["aws:ResourceTag/${TagKey}"]}],"conditionKeys":{"aws:RequestTag/${TagKey}":{"name":"aws:RequestTag/${TagKey}","types":["String"],"description":"Filters access by the tags that are passed in the request"},"aws:ResourceTag/${TagKey}":{"name":"aws:ResourceTag/${TagKey}","types":["String"],"description":"Filters access by the tags associated with the resource"},"aws:TagKeys":{"name":"aws:TagKeys","types":["ArrayOfString"],"description":"Filters access by the tag keys that are passed in the request"}},"url":"https://docs.aws.amazon.com/service-authorization/latest/reference/list_awsoutposts.html"}